omlt/__init__.py
omlt/_version.py
omlt/block.py
omlt/dependencies.py
omlt/formulation.py
omlt/py.typed
omlt/scaling.py
omlt/gbt/__init__.py
omlt/gbt/gbt_formulation.py
omlt/gbt/model.py
omlt/io/__init__.py
omlt/io/input_bounds.py
omlt/io/onnx.py
omlt/io/onnx_parser.py
omlt/io/keras/__init__.py
omlt/io/keras/keras_reader.py
omlt/io/torch_geometric/__init__.py
omlt/io/torch_geometric/build_gnn_formulation.py
omlt/io/torch_geometric/torch_geometric_reader.py
omlt/linear_tree/__init__.py
omlt/linear_tree/lt_definition.py
omlt/linear_tree/lt_formulation.py
omlt/neuralnet/__init__.py
omlt/neuralnet/layer.py
omlt/neuralnet/network_definition.py
omlt/neuralnet/nn_formulation.py
omlt/neuralnet/activations/__init__.py
omlt/neuralnet/activations/linear.py
omlt/neuralnet/activations/relu.py
omlt/neuralnet/activations/smooth.py
omlt/neuralnet/layers/__init__.py
omlt/neuralnet/layers/full_space.py
omlt/neuralnet/layers/partition_based.py
omlt/neuralnet/layers/reduced_space.py
omlt-1.2.2.dist-info/licenses/LICENSE.rst
omlt-1.2.2.dist-info/METADATA
omlt-1.2.2.dist-info/WHEEL
omlt-1.2.2.dist-info/top_level.txt
omlt-1.2.2.dist-info/RECORD
