Metadata-Version: 2.4
Name: omlt
Version: 1.2.2
Summary: OMLT is a Python package for representing machine learning models (such as neural networks) within the Pyomo optimization environment.
Author-email: The OMLT Developers <omlt@googlegroups.com>
License: =================
Project-URL: github, https://github.com/cog-imperial/OMLT
Project-URL: x, https://x.com/cogimperial
Project-URL: documentation, https://omlt.readthedocs.io
Requires-Python: >=3.9
License-File: LICENSE.rst
Requires-Dist: networkx
Requires-Dist: numpy
Requires-Dist: pyomo>=6.7.3
Requires-Dist: onnx
Requires-Dist: onnxruntime
Provides-Extra: linear-tree
Requires-Dist: linear-tree; extra == "linear-tree"
Provides-Extra: keras
Requires-Dist: tensorflow; extra == "keras"
Requires-Dist: keras; extra == "keras"
Provides-Extra: keras-gpu
Requires-Dist: tensorflow[and-cuda]; extra == "keras-gpu"
Requires-Dist: keras; extra == "keras-gpu"
Provides-Extra: torch
Requires-Dist: torch; extra == "torch"
Requires-Dist: torch-geometric; extra == "torch"
Provides-Extra: dev-tools
Requires-Dist: ruff; extra == "dev-tools"
Requires-Dist: mypy; extra == "dev-tools"
Requires-Dist: pytest; extra == "dev-tools"
Requires-Dist: pytest-cov; extra == "dev-tools"
Requires-Dist: sphinx; extra == "dev-tools"
Requires-Dist: sphinx-copybutton; extra == "dev-tools"
Requires-Dist: build; extra == "dev-tools"
Requires-Dist: twine; extra == "dev-tools"
Requires-Dist: furo; extra == "dev-tools"
Requires-Dist: testbook; extra == "dev-tools"
Requires-Dist: notebook; extra == "dev-tools"
Requires-Dist: pandas; extra == "dev-tools"
Requires-Dist: matplotlib; extra == "dev-tools"
Requires-Dist: gurobipy; extra == "dev-tools"
Requires-Dist: torchvision; extra == "dev-tools"
Requires-Dist: tf2onnx; extra == "dev-tools"
Provides-Extra: docs
Requires-Dist: sphinx; extra == "docs"
Requires-Dist: sphinx-rtd-theme; extra == "docs"
Requires-Dist: tensorflow; extra == "docs"
Requires-Dist: linear-tree; extra == "docs"
Provides-Extra: dev
Requires-Dist: omlt[dev-tools,docs,keras,linear-tree,torch]; extra == "dev"
Provides-Extra: dev-gpu
Requires-Dist: omlt[dev-tools,docs,keras-gpu,linear-tree,torch]; extra == "dev-gpu"
Dynamic: license-file
